torchstream/__init__.py
torchstream/exception_signature.py
torchstream/perf_thingy.py
torchstream/stream.py
torchstream/stream_equivalence.py
torchstream/patching/call_identification.py
torchstream/patching/call_intercept.py
torchstream/sequence/__init__.py
torchstream/sequence/array_interface.py
torchstream/sequence/dtype.py
torchstream/sequence/seq_spec.py
torchstream/sequence/sequence.py
torchstream/sequence/sequential_array.py
torchstream/sliding_window/dummy_sliding_window_transform.py
torchstream/sliding_window/kernel_sparsity.py
torchstream/sliding_window/nan_trick.py
torchstream/sliding_window/sliding_window_in_out_size_sampler.py
torchstream/sliding_window/sliding_window_params.py
torchstream/sliding_window/sliding_window_params_sampler.py
torchstream/sliding_window/sliding_window_params_solver.py
torchstream/sliding_window/sliding_window_stream.py
torchstream/sliding_window/threshold_harvester.py
torchstream/sliding_window/transforms.py
torchstream/sliding_window/z3_utils.py
torchstream_lib-1.0.2.dist-info/licenses/LICENSE
torchstream_lib-1.0.2.dist-info/METADATA
torchstream_lib-1.0.2.dist-info/WHEEL
torchstream_lib-1.0.2.dist-info/top_level.txt
torchstream_lib-1.0.2.dist-info/RECORD
