Metadata-Version: 2.4
Name: torchstream-lib
Version: 1.0.2
Summary: A library for making PyTorch models streamable
Author-email: Corentin Jemine <corentin.jemine@gmail.com>
Maintainer-email: Corentin Jemine <corentin.jemine@gmail.com>
License-Expression: MIT
Project-URL: Repository, https://github.com/CorentinJ/TorchStream
Keywords: torch,pytorch,streaming,deep learning,machine learning,neural networks,numpy,optimization
Classifier: Programming Language :: Python :: 3
Classifier: Operating System :: OS Independent
Classifier: Intended Audience :: Developers
Classifier: Intended Audience :: Science/Research
Classifier: Topic :: Scientific/Engineering :: Artificial Intelligence
Classifier: Topic :: Software Development :: Libraries
Classifier: Framework :: OpenTelemetry :: Instrumentations
Requires-Python: >=3.8
License-File: LICENSE
Requires-Dist: numpy>=1.23.0
Requires-Dist: opentelemetry-api>=1.33.1
Requires-Dist: scipy>=1.10.1
Requires-Dist: torch>=1.11.0
Requires-Dist: z3-solver>=4.14.0.0
Provides-Extra: cpu
Requires-Dist: torch>=1.11.0; extra == "cpu"
Provides-Extra: cuda
Requires-Dist: torch>=1.11.0; extra == "cuda"
Dynamic: license-file
